bimmoe-1.0.2.dist-info/licenses/LICENSE
qdt_bimmoe/__init__.py
qdt_bimmoe/core.py
bimmoe-1.0.2.dist-info/METADATA
bimmoe-1.0.2.dist-info/WHEEL
bimmoe-1.0.2.dist-info/entry_points.txt
bimmoe-1.0.2.dist-info/top_level.txt
bimmoe-1.0.2.dist-info/RECORD
