Metadata-Version: 2.4
Name: bimmoe
Version: 1.0.2
Summary: Quantum Duality Theory (QDT) Bidirectional Multi-Modal Multi-Expert Framework
Author-email: QDT Research Team <research@qdt-framework.org>
Maintainer-email: QDT Research Team <research@qdt-framework.org>
License: MIT
Project-URL: Homepage, https://github.com/beanapologist/BiMMoE
Project-URL: Documentation, https://github.com/beanapologist/BiMMoE#readme
Project-URL: Repository, https://github.com/beanapologist/BiMMoE
Project-URL: Bug-Tracker, https://github.com/beanapologist/BiMMoE/issues
Keywords: quantum,multi-modal,machine learning,physics,energy,tokenization
Classifier: Development Status :: 5 - Production/Stable
Classifier: Intended Audience :: Science/Research
Classifier: License :: OSI Approved :: MIT License
Classifier: Operating System :: OS Independent
Classifier: Programming Language :: Python :: 3
Classifier: Programming Language :: Python :: 3.8
Classifier: Programming Language :: Python :: 3.9
Classifier: Programming Language :: Python :: 3.10
Classifier: Programming Language :: Python :: 3.11
Classifier: Topic :: Scientific/Engineering :: Artificial Intelligence
Classifier: Topic :: Scientific/Engineering :: Physics
Classifier: Topic :: Software Development :: Libraries :: Python Modules
Requires-Python: >=3.8
License-File: LICENSE
Requires-Dist: numpy>=1.21.0
Provides-Extra: dev
Requires-Dist: pytest>=6.0; extra == "dev"
Requires-Dist: pytest-cov>=2.0; extra == "dev"
Requires-Dist: black>=21.0; extra == "dev"
Requires-Dist: flake8>=3.8; extra == "dev"
Requires-Dist: mypy>=0.800; extra == "dev"
Provides-Extra: docs
Requires-Dist: sphinx>=4.0; extra == "docs"
Requires-Dist: sphinx-rtd-theme>=1.0; extra == "docs"
Dynamic: license-file
